_lacbd.cpython-36m-x86_64-linux-gnu.so
_lacbd.cpython-37m-x86_64-linux-gnu.so
lacbd-0.2.0.dist-info/top_level.txt
lacbd-0.2.0.dist-info/WHEEL
lacbd-0.2.0.dist-info/METADATA
lacbd-0.2.0.dist-info/RECORD
lacbd/__init__.py
