Metadata-Version: 2.1
Name: lacbd
Version: 0.2.0
Summary: Fast subsentence searching
Home-page: https://github.com/nitros12/like-aho-corasick-but-different-py
Author: Ben Simms, Ben Mintz
Author-email: ben@bensimms.moe, bmintz@protonmail.com
License: AGPL-3.0-or-later
Platform: UNKNOWN
Classifier: Development Status :: 4 - Beta
Classifier: Operating System :: POSIX
Classifier: Operating System :: Microsoft :: Windows
Classifier: License :: OSI Approved :: GNU Affero General Public License v3 or later (AGPLv3+)
Classifier: Programming Language :: Rust
Classifier: Programming Language :: C
Classifier: Programming Language :: Python
Classifier: Programming Language :: Python :: 3 :: Only
Classifier: Programming Language :: Python :: 3.6
Classifier: Programming Language :: Python :: 3.7
Classifier: Programming Language :: Python :: 3.8
Classifier: Topic :: Software Development :: Libraries :: Python Modules
Requires-Python: >=3.6
